pysen/__init__.py
pysen/__main__.py
pysen/_version.py
pysen/black.py
pysen/cli.py
pysen/cli_config.py
pysen/command.py
pysen/component.py
pysen/diagnostic.py
pysen/dist_version.py
pysen/dumper.py
pysen/error_lines.py
pysen/exceptions.py
pysen/factory.py
pysen/flake8.py
pysen/git_utils.py
pysen/isort.py
pysen/lint_command.py
pysen/logging_utils.py
pysen/manifest.py
pysen/manifest_builder.py
pysen/mypy.py
pysen/path.py
pysen/plugin.py
pysen/plugin_loader.py
pysen/process_utils.py
pysen/py.typed
pysen/py_module.py
pysen/py_version.py
pysen/pyproject.py
pysen/pyproject_model.py
pysen/reporter.py
pysen/runner.py
pysen/runner_options.py
pysen/setting.py
pysen/source.py
pysen/types.py
pysen/ext/__init__.py
pysen/ext/black_wrapper.py
pysen/ext/flake8_wrapper.py
pysen/ext/isort_wrapper.py
pysen/ext/mypy_wrapper.py
pysen-0.12.0.dist-info/METADATA
pysen-0.12.0.dist-info/WHEEL
pysen-0.12.0.dist-info/entry_points.txt
pysen-0.12.0.dist-info/licenses/LICENSE
pysen-0.12.0.dist-info/RECORD
