Metadata-Version: 2.4
Name: pysen
Version: 0.12.0
Summary: Python linting made easy. Also a casual yet honorific way to address individuals who have entered an organization prior to you.
Project-URL: Repository, https://github.com/pfnet/pysen.git
Author-email: Yuki Igarashi <me@bonprosoft.com>, Toru Ogawa <ogawa@preferred.jp>, Ryo Miyajima <ryo@preferred.jp>, Linsho Kaku <linsho@preferred.jp>
License-Expression: MIT
License-File: LICENSE
Classifier: License :: OSI Approved :: MIT License
Classifier: Operating System :: MacOS
Classifier: Operating System :: POSIX
Classifier: Operating System :: Unix
Classifier: Programming Language :: Python
Classifier: Programming Language :: Python :: 3.10
Classifier: Programming Language :: Python :: 3.11
Classifier: Programming Language :: Python :: 3.12
Classifier: Programming Language :: Python :: 3.13
Classifier: Programming Language :: Python :: 3.14
Requires-Python: >=3.10
Requires-Dist: colorlog<5.0.0,>=4.0.0
Requires-Dist: dacite<2.0.0,>=1.1.0
Requires-Dist: gitpython<4.0.0,>=3.0.0
Requires-Dist: tomlkit<1.0.0,>=0.5.11
Requires-Dist: unidiff<1.0.0,>=0.6.0
Provides-Extra: lint
Requires-Dist: black<=22.10,>=19.10b0; extra == 'lint'
Requires-Dist: flake8-bugbear; extra == 'lint'
Requires-Dist: flake8<5,>=3.7; extra == 'lint'
Requires-Dist: isort<5.2.0,>=4.3; extra == 'lint'
Requires-Dist: mypy<0.800,>=0.770; extra == 'lint'
